mux21-struc/m_mux21.v
// 结构化建模
module m_mux21(a,b,s,y);
    input a,b,s;
    output y;

    wire l,r,s_n; // 内部网线声明
    my_not i1(.a(s),   .b(s_n)); // 实例化非门
    my_and i2(.a(s_n), .b(a), .c(l)); // 实例化与门，实现(~s&a)
    my_and i3(.a(s),   .b(b), .c(r)); // 实例化与门，实现(s&b)
    my_or  i4(.a(l),   .b(r), .c(y)); // 实例化或门，实现(~s&a)|(s&b)
endmodule

/* verilator lint_off DECLFILENAME */
module my_and(a,b,c);
    input a,b;
    output c;

    assign c=a&b;
endmodule

module my_or (a,b,c);
    input a,b;
    output c;
    assign c=a|b;
endmodule

module my_not(a,b);
  input  a;
  output b;

  assign b = ~a;
endmodule

mux21-struc/dump.vcd
$version Generated by VerilatedVcd $end
$timescale 1s $end
 $scope module TOP $end
  $var wire 1 # a $end
  $var wire 1 $ b $end
  $var wire 1 % s $end
  $var wire 1 & y $end
  $scope module m_mux21 $end
   $var wire 1 # a $end
   $var wire 1 $ b $end
   $var wire 1 % s $end
   $var wire 1 & y $end
   $var wire 1 ' l $end
   $var wire 1 ( r $end
   $var wire 1 ) s_n $end
   $scope module i1 $end
    $var wire 1 % a $end
    $var wire 1 ) b $end
   $upscope $end
   $scope module i2 $end
    $var wire 1 ) a $end
    $var wire 1 # b $end
    $var wire 1 ' c $end
   $upscope $end
   $scope module i3 $end
    $var wire 1 % a $end
    $var wire 1 $ b $end
    $var wire 1 ( c $end
   $upscope $end
   $scope module i4 $end
    $var wire 1 ' a $end
    $var wire 1 ( b $end
    $var wire 1 & c $end
   $upscope $end
  $upscope $end
 $upscope $end
$enddefinitions $end


#1
0#
0$
0%
0&
0'
0(
1)
#2
1$
#3
1#
0$
1&
1'
#4
1$
#5
0#
0$
1%
0&
0'
0)
#6
1$
1&
1(
#7
1#
0$
0&
0(
#8
1$
1&
1(
