NJUlab2/Fadd-8/FA_1.v
module FA_1(
    input A,     // 输入信号 A
    input B,     // 输入信号 B
    input Cin,   // 输入进位信号 Cin
    output Sum,  // 输出和信号 Sum
    output Cout  // 输出进位信号 Cout
);

assign Sum=A^B^Cin;
assign Cout=(A&B)|(A&Cin)|(B&Cin);

endmodule

NJUlab2/Fadd-8/top.v
`include "FA_1.v"

module top(
    input [7:0] x, y,
    input cin,
    output [7:0] f,
    output cout
);

    wire [8:0] c;
    assign c[0] = cin;
    FA_1 fa0(x[0], y[0], c[0], f[0], c[1]);
    FA_1 fa1(x[1], y[1], c[1], f[1], c[2]);
    FA_1 fa2(x[2], y[2], c[2], f[2], c[3]);
    FA_1 fa3(x[3], y[3], c[3], f[3], c[4]);
    FA_1 fa4(x[4], y[4], c[4], f[4], c[5]); // 修复此处
    FA_1 fa5(x[5], y[5], c[5], f[5], c[6]); // 修复此处
    FA_1 fa6(x[6], y[6], c[6], f[6], c[7]); // 修复此处
    FA_1 fa7(x[7], y[7], c[7], f[7], c[8]); // 修复此处

    assign cout = c[8];

endmodule

NJUlab2/Fadd-8/dump.vcd
$version Generated by VerilatedVcd $end
$timescale 1s $end
 $scope module TOP $end
  $var wire 8 * x [7:0] $end
  $var wire 8 + y [7:0] $end
  $var wire 1 , cin $end
  $var wire 8 - f [7:0] $end
  $var wire 1 . cout $end
  $scope module top $end
   $var wire 8 * x [7:0] $end
   $var wire 8 + y [7:0] $end
   $var wire 1 , cin $end
   $var wire 8 - f [7:0] $end
   $var wire 1 . cout $end
   $var wire 9 / c [8:0] $end
   $scope module fa0 $end
    $var wire 1 0 A $end
    $var wire 1 1 B $end
    $var wire 1 , Cin $end
    $var wire 1 2 Sum $end
    $var wire 1 # Cout $end
   $upscope $end
   $scope module fa1 $end
    $var wire 1 3 A $end
    $var wire 1 4 B $end
    $var wire 1 # Cin $end
    $var wire 1 5 Sum $end
    $var wire 1 $ Cout $end
   $upscope $end
   $scope module fa2 $end
    $var wire 1 6 A $end
    $var wire 1 7 B $end
    $var wire 1 $ Cin $end
    $var wire 1 8 Sum $end
    $var wire 1 % Cout $end
   $upscope $end
   $scope module fa3 $end
    $var wire 1 9 A $end
    $var wire 1 : B $end
    $var wire 1 % Cin $end
    $var wire 1 ; Sum $end
    $var wire 1 & Cout $end
   $upscope $end
   $scope module fa4 $end
    $var wire 1 < A $end
    $var wire 1 = B $end
    $var wire 1 & Cin $end
    $var wire 1 > Sum $end
    $var wire 1 ' Cout $end
   $upscope $end
   $scope module fa5 $end
    $var wire 1 ? A $end
    $var wire 1 @ B $end
    $var wire 1 ' Cin $end
    $var wire 1 A Sum $end
    $var wire 1 ( Cout $end
   $upscope $end
   $scope module fa6 $end
    $var wire 1 B A $end
    $var wire 1 C B $end
    $var wire 1 ( Cin $end
    $var wire 1 D Sum $end
    $var wire 1 ) Cout $end
   $upscope $end
   $scope module fa7 $end
    $var wire 1 E A $end
    $var wire 1 F B $end
    $var wire 1 ) Cin $end
    $var wire 1 G Sum $end
    $var wire 1 . Cout $end
   $upscope $end
  $upscope $end
 $upscope $end
$enddefinitions $end


#1
1#
1$
1%
1&
1'
0(
0)
b00011111 *
b00001001 +
0,
b00101000 -
0.
b000111110 /
10
11
02
13
04
05
16
07
08
19
1:
1;
1<
0=
0>
0?
0@
1A
0B
0C
0D
0E
0F
0G
#2
b01000111 *
b00011011 +
1,
b01100011 -
b000111111 /
12
14
15
09
0;
0<
1=
1B
1D
#3
0%
0'
1(
b00101011 *
b10101000 +
b11010100 -
b001010111 /
01
02
04
05
06
18
19
0=
1>
1?
1@
0A
0B
1F
1G
#4
0#
1%
0(
b00000110 *
b01101011 +
0,
b01110001 -
b000011100 /
00
11
12
14
16
08
09
0?
1A
1C
0F
0G
#5
0$
0%
0&
1'
1(
1)
b00011001 *
b01110000 +
b10001001 -
b011100000 /
10
01
03
04
06
19
0:
1;
1<
1=
0>
0A
0D
1G
#6
1#
1$
1%
1&
0(
0)
b11011101 *
b10000011 +
b01100000 -
1.
b100111110 /
11
02
14
16
0;
0=
0@
1A
1B
0C
1D
1E
1F
0G
#7
0%
1(
1)
b00111000 *
b01001011 +
1,
b10000100 -
0.
b011110111 /
00
06
18
1:
1?
0A
0B
1C
0D
0E
0F
1G
#8
0#
0$
1%
b11101101 *
b00111110 +
0,
b00101011 -
1.
b111111000 /
10
01
12
15
16
17
08
1;
0<
1=
1@
1A
1B
0C
1E
0G
#9
1#
1$
0(
0)
b00001101 *
b11011010 +
1,
b11101000 -
0.
b000111111 /
02
05
07
0?
0@
0B
1C
1D
0E
1F
1G
#10
1(
1)
b01111111 *
b10111111 +
b00111111 -
1.
b111111111 /
11
12
13
15
17
18
1<
1>
1?
1@
1B
0C
0D
0G
#11
0#
b10111010 *
b11111110 +
0,
b10111000 -
b111111100 /
00
01
02
05
06
08
0B
1C
1E
1G
#12
0$
0%
0&
0'
0(
0)
b10000001 *
b01100110 +
b11100111 -
0.
b000000000 /
10
12
03
15
18
09
0:
0;
0<
0=
0>
0?
1D
0F
#13
1#
1$
1(
1)
b00101011 *
b01110001 +
1,
b10011101 -
b011000111 /
11
13
04
05
07
19
1;
1=
1>
1?
0A
0D
0E
#14
1%
b01100111 *
b10100101 +
b00001101 -
1.
b111001111 /
16
17
09
0=
0>
1B
0C
1F
0G
#15
0#
0$
0%
0)
b10110100 *
b10100001 +
0,
b01010101 -
b101000000 /
00
03
07
0;
1<
1>
0B
1D
1E
#16
1$
1%
1&
1'
1)
b01101110 *
b01011110 +
1,
b11001101 -
0.
b011111101 /
01
13
14
17
19
1:
1;
0<
1=
0>
0@
1B
1C
0E
0F
1G
#17
1#
0)
b00101110 *
b10011101 +
b11001100 -
b001111111 /
11
02
04
0B
0C
1F
#18
0#
0$
0%
0&
0'
0(
b01100000 *
b00010110 +
0,
b01110110 -
b000000000 /
01
03
14
15
06
09
0:
0;
1>
1A
1B
0F
0G
#19
1'
1(
1)
b01010110 *
b00111001 +
b10001111 -
b011100000 /
11
12
13
04
16
07
1:
1;
1<
0>
0?
1@
0A
0D
1G
#20
1#
1$
1%
1&
0'
0(
0)
b11101111 *
b00001011 +
1,
b11111011 -
b000011111 /
10
14
08
19
0<
0=
1>
1?
0@
1A
1D
1E
